bullhorn/__init__.py
bullhorn/client.py
bullhorn/exceptions.py
bullhorn/route.py
bullhorn/types/__init__.py
bullhorn/types/agreement_line.py
bullhorn/types/appointment.py
bullhorn/types/billing_profile.py
bullhorn/types/branch.py
bullhorn/types/business_sector.py
bullhorn/types/candidate.py
bullhorn/types/category.py
bullhorn/types/client_contact.py
bullhorn/types/client_corporation.py
bullhorn/types/client_corporation_appointment.py
bullhorn/types/corporate_user.py
bullhorn/types/country.py
bullhorn/types/department.py
bullhorn/types/employee_pay.py
bullhorn/types/employer_contribution.py
bullhorn/types/job_code.py
bullhorn/types/job_order.py
bullhorn/types/job_submission.py
bullhorn/types/job_submission_history.py
bullhorn/types/lead.py
bullhorn/types/lead_history.py
bullhorn/types/location.py
bullhorn/types/opportunity.py
bullhorn/types/opportunity_history.py
bullhorn/types/person.py
bullhorn/types/ping.py
bullhorn/types/placement.py
bullhorn/types/placement_commission.py
bullhorn/types/sendout.py
bullhorn/types/setting.py
bullhorn/types/shift.py
bullhorn/types/workers_compensation.py
bullhorn/types/workers_compensation_rate.py
examples/__init__.py
examples/get_placements_and_candidates.py
tests/__init__.py
tests/test_client.py
tests/test_route.py
bullhorn-0.0.12.dist-info/LICENSE
bullhorn-0.0.12.dist-info/METADATA
bullhorn-0.0.12.dist-info/WHEEL
bullhorn-0.0.12.dist-info/top_level.txt
bullhorn-0.0.12.dist-info/RECORD
