Metadata-Version: 2.1
Name: bullhorn
Version: 0.0.12
Summary: Python wrapper for the Bullhorn REST API
Home-page: https://github.com/recruithub/bullhorn
Author: lloydtao
Author-email: lewis@recruit-hub.com
License: MIT
Classifier: Programming Language :: Python :: 3
Classifier: License :: OSI Approved :: MIT License
Classifier: Operating System :: OS Independent
Requires-Python: >=3.10
License-File: LICENSE
Requires-Dist: requests (<3,>=2)
